scylla/__init__.py
scylla/downloader.py
scylla/main.py
scylla/progress.py
scylla_http-1.0.0.dist-info/METADATA
scylla_http-1.0.0.dist-info/WHEEL
scylla_http-1.0.0.dist-info/entry_points.txt
scylla_http-1.0.0.dist-info/top_level.txt
scylla_http-1.0.0.dist-info/RECORD
