Metadata-Version: 2.1
Name: scylla-http
Version: 1.0.0
Summary: The parallel downloader.
Home-page: https://github.com/kazaamjt/Scylla
Author: kazaamjt
Author-email: kazaamjt@gmail.com
License: MIT
Platform: UNKNOWN
Classifier: Programming Language :: Python :: 3
Classifier: License :: OSI Approved :: MIT License
Classifier: Operating System :: OS Independent
Requires-Python: >=3.9
Requires-Dist: aiohttp (==3.7.4.post0)
Requires-Dist: click (==8.0.1)
